README
setup.py
testmachine/__init__.py
testmachine/common.py
testmachine/context.py
testmachine/examples_test.py
testmachine/operations.py
testmachine/testmachine.py
testmachine/testmachine_test.py
testmachine.egg-info/PKG-INFO
testmachine.egg-info/SOURCES.txt
testmachine.egg-info/dependency_links.txt
testmachine.egg-info/top_level.txt