Metadata-Version: 1.0
Name: testmachine
Version: 0.0.5
Summary: Stack based automatic testcase generation
Home-page: https://github.com/DRMacIver/testmachine
Author: David R. MacIver
Author-email: david@drmaciver.com
License: LICENSE.txt
Platform: UNKNOWN
